[
  {
    "name": "Сладкий овсяноблин",
    "type": "завтрак",
    "time": "",
    "ingredients": [
      "Овсянка - 40 г",
      "Яйцо - 1 шт",
      "Молоко 1,5% - 60 мл",
      "Сахарозаменитель - по вкусу",
      "Банан - ½ шт",
      "Творог мягкий 5% - 85 г"
    ],
    "instructions": [
      "Смешать овсянку, яйцо, молоко и подсластитель",
      "Для гладкого блина взбить все блендером",
      "Выпекать блин на раскаленной сковороде с обеих сторон",
      "Готовый блин смазать мягким творогом и добавить нарезанный банан",
      "Количество ингредиентов рассчитано на 1 раз (1 человека)"
    ]
  },
  {
    "name": "Оладьи с ягодами",
    "type": "завтрак",
    "time": "",
    "ingredients": [
      "Яйцо - 2 шт (1 целое яйцо и 1 белок)",
      "Сметана 15% - 100 г",
      "Рисовая мука - 100 г",
      "Черника - 60 г (или любые ягоды)",
      "Сахарозаменитель - по вкусу",
      "Разрыхлитель - ½ ч.л",
      "Ванилин - по вкусу",
      "Соль - щепотка",
      "Мёд - 20 г"
    ],
    "instructions": [
      "Разбить 1 яйцо, добавить белок одного яйца",
      "Взбить яйца с щепоткой соли венчиком",
      "К яйцам просеять муку, добавить сметану, разрыхлитель, сахарозаменитель, ванилин, ягоды",
      "Все перемешать",
      "Жарить оладьи с двух сторон на антипригарной сковороде без масла",
      "Получившиеся оладушки разделить на 2 порции",
      "Каждую порцию при подаче полить 10 г мёда (по желанию)"
    ]
  },
  {
    "name": "Кокосовые сырники",
    "type": "завтрак",
    "time": "",
    "ingredients": [
      "Творог 2% в брикетах - 200 г",
      "Яйцо куриное - 1 шт",
      "Мука рисовая - 50 г + 10 г для обвалки",
      "Кокосовая стружка - 20 г (можно заменить на мак или убрать)",
      "Сахарозаменитель - по вкусу",
      "Ванилин - по вкусу"
    ],
    "instructions": [
      "В миске смешать творог, отделить белок от желтка",
      "В тесто добавить только желток - белок не нужен",
      "Добавить муку, кокосовую стружку, сахарозаменитель и ванилин",
      "Вымешать тесто до получения плотного, мягкого и однородного творожного комка",
      "Слегка влажными руками слепить шарик, обвалять в муке",
      "Сформировать сырники и жарить на антипригарной сковороде под крышкой на небольшом огне",
      "Рецепт рассчитан на 2 раза (2 человек)"
    ]
  },
  {
    "name": "Сэндвич с яйцом и сыром",
    "type": "завтрак",
    "time": "",
    "ingredients": [
      "Хлеб зерновой - 4 шт по 25 г",
      "Яйцо вареное - 2 шт",
      "Сыр легкий - 80 г",
      "Огурец - 200 г"
    ],
    "instructions": [
      "Собрать два бутерброда: хлеб 25 г + сыр 40 г + яйцо 1 шт + хлеб 25 г, и еще раз также",
      "Разрезать каждый по диагонали - получится 4 кусочка",
      "Два кусочка и огурец 100 г убрать на завтра",
      "Остальные два кусочка разогреть в тостере/микроволновке",
      "Есть вместе с огурчиком",
      "Количество ингредиентов рассчитано на 2 раза (2 человек)"
    ]
  },
  {
    "name": "Омлет с овощами и сыром",
    "type": "завтрак",
    "time": "",
    "ingredients": [
      "Яйцо - 6 шт",
      "Молоко 0,5% - 200 мл",
      "Сыр легкий - 60 г",
      "Перец болгарский - 100 г",
      "Помидор - 50 г",
      "Лук репчатый - 30 г",
      "Соль/перец - по вкусу"
    ],
    "instructions": [
      "Яйца взбить с молоком, добавить специи по вкусу",
      "Овощи нарезать удобным форматом",
      "Разогреть антипригарную сковороду",
      "Обжарить овощи 2-3 минуты",
      "Влить к овощам яичную смесь",
      "Добавить укроп/петрушку по вкусу",
      "Накрыть сковороду крышкой и готовить омлет на среднем огне до готовности около 10 минут",
      "Готовый омлет разрезать пополам"
    ]
  },
  {
    "name": "Ленивая овсянка в банке с фруктами",
    "type": "завтрак",
    "time": "готовить вечером накануне",
    "ingredients": [
      "Овсянка - 100 г",
      "Йогурт натуральный - 160 г",
      "Банан - 70 г",
      "Клубника - 70 г",
      "Миндаль - 20 г",
      "Подсластитель - по вкусу"
    ],
    "instructions": [
      "На 2 банки распределить все ингредиенты",
      "В йогурт натуральный добавить подсластитель",
      "Выкладывать слоями: овсянка, затем йогурт, банан, овсянка, йогурт, клубника, йогурт и сверху миндаль",
      "Убрать в холодильник на ночь",
      "Количество ингредиентов рассчитано на 2 раза (2 человек)"
    ]
  },
  {
    "name": "Сырные лепешки с зеленью",
    "type": "завтрак",
    "time": "",
    "ingredients": [
      "Сыр - 60 г",
      "Мука рисовая - 60 г",
      "Яйцо - 2 шт",
      "Творог мягкий 5% - 120 г",
      "Укроп/зеленый лук - по вкусу",
      "Соль - по вкусу"
    ],
    "instructions": [
      "Добавить в мягкий творог яйца, взбить венчиком до однородной массы",
      "Сыр натереть, зелень мелко нарезать",
      "В яично-творожную смесь добавить сыр, зелень, муку, немного соли",
      "Тщательно перемешать",
      "Обжаривать на антипригарной сковороде с двух сторон в виде небольших лепешек до готовности",
      "При подаче на стол посыпать укропом",
      "Рецепт рассчитан на 2 раза (2 человек)"
    ]
  },
  {
    "name": "Кесадилья с шампиньонами",
    "type": "завтрак",
    "time": "",
    "ingredients": [
      "Лаваш - 60 г",
      "Молоко 1,5% - 20 мл",
      "Шампиньоны - 150 г",
      "Помидор - 150 г",
      "Сыр - 30 г",
      "Масло растительное - 5 г"
    ],
    "instructions": [
      "Шампиньоны и томаты тушить на антипригарной сковороде",
      "Вырезать лаваш по диаметру сковороды (примерно 60 г)",
      "Смазать сковороду каплей масла",
      "На лаваш выложить тушеные овощи",
      "Смешать яйцо, молоко и специи",
      "Вылить на лаваш",
      "Через минуту добавить тертый сыр, накрыть крышкой",
      "Когда яично-молочная смесь схватится, сложить пополам и перевернуть",
      "Ингредиенты указаны на 1 порцию"
    ]
  },
  {
    "name": "Запеканка-чизкейк",
    "type": "завтрак",
    "time": "",
    "ingredients": [
      "Творог мягкий 5% - 350 г",
      "Мука рисовая - 65 г",
      "Яйцо - 2 шт",
      "Кефир 1% - 45 г",
      "Разрыхлитель - ½ ч.л",
      "Ванилин/подсластитель - по вкусу"
    ],
    "instructions": [
      "Смешать 200 г творога, муку, яйца, кефир, разрыхлитель",
      "Добавить по вкусу сахарозаменитель и ванилин, перемешать",
      "Перелить тесто в форму (лучше взять форму повыше)",
      "Отправить в микроволновку на 7 минут",
      "Периодически останавливать микроволновку, когда тесто поднимается",
      "Готовое тесто вытащить и дать остыть",
      "Для крема смешать мягкий творог и подсластитель",
      "Тесто разрезать на 2 части",
      "Смазать кремом между коржами и сверху",
      "По желанию украсить ягодами и какао/кокосовой стружкой"
    ]
  },
  {
    "name": "Рисовая каша с ягодами + яйцо",
    "type": "завтрак",
    "time": "",
    "ingredients": [
      "Рис - 100 г (в сухом виде)",
      "Молоко 1,5% - 400 мл",
      "Клубника - 150 г (или другие фрукты/ягоды)",
      "Мёд - 18 г",
      "Яйцо - 2 шт"
    ],
    "instructions": [
      "Сварить рисовую кашу на молоке",
      "Отварить яйца",
      "Получившуюся порцию каши разделить пополам на 2 раза",
      "К каждой порции каши добавить 75 г клубники и 9 г мёда",
      "Добавить к завтраку по 1 яйцу",
      "Количество ингредиентов рассчитано на 2 раза (2 человек)"
    ]
  },
  {
    "name": "ПП-Хачапури по-аджарски",
    "type": "обед",
    "time": "",
    "ingredients": [
      "Творог 2% в брикетах - 200 г",
      "Яйцо - 1 шт",
      "Мука рисовая - 50 г",
      "Соль - по вкусу",
      "Яйцо - 1 шт (для начинки)",
      "Творог 2% в брикетах - 30 г (для начинки)",
      "Сыр сулугуни - 50 г (для начинки)"
    ],
    "instructions": [
      "Белок отделить от желтка. Желток оставить для позднейшего использования",
      "Смешать 200 г творога с белком",
      "Добавить рисовую муку и соль по вкусу",
      "Замесить тесто",
      "Из теста сформировать лодочку (одну большую или 2 маленькие) с углублением посередине и бортиками",
      "Смазать лодочку желтком",
      "Отправить в разогретую духовку на 10 минут",
      "Сыр натереть на крупной терке",
      "Смешать для начинки 30 г творога и сыр",
      "Достать лодочку из духовки, добавить начинку и отправить в духовку еще на 10 минут",
      "Достать лодочку, в центр добавить яйцо",
      "Снова отправить в духовку на 3-5 минут (белок должен схватиться, желток остаться жидким)"
    ]
  },
  {
    "name": "Паста с курицей в сливочном соусе",
    "type": "обед",
    "time": "",
    "ingredients": [
      "Спагетти - 140 г (в сухом виде)",
      "Желток одного яйца",
      "Сливки 10% - 90 г",
      "Сыр легкий - 30 г",
      "Куриная грудка - 120 г",
      "Масло растительное - 5 г",
      "Чеснок - 1 зубчик",
      "Соль/перец - по вкусу",
      "Зелень (укроп/петрушка) - по вкусу"
    ],
    "instructions": [
      "Отварить спагетти",
      "Куриную грудку нарезать, посолить, обжарить без масла",
      "На капле растительного масла обжарить чеснок",
      "Влить сливки, прогреть с чесноком",
      "Добавить желток яйца, соль, перец, зелень по вкусу",
      "Добавить курицу",
      "Снять с огня, в соус добавить спагетти",
      "Перед подачей посыпать тертым сыром"
    ]
  },
  {
    "name": "Тефтели из индейки с гречкой",
    "type": "обед",
    "time": "",
    "ingredients": [
      "Индейка грудка - 200 г",
      "Кабачок - 60 г",
      "Овсянка - 15 г",
      "Яйцо - 1 шт",
      "Чеснок - 1 зубчик",
      "Гречка - 100 г (в сухом виде)",
      "Помидор - 200 г",
      "Масло растительное - 5 г",
      "Соль/специи - по вкусу"
    ],
    "instructions": [
      "Из индейки сделать фарш",
      "Натереть на тёрке кабачок, отжать лишнюю воду и смешать с фаршем",
      "Добавить молотую овсянку, яйцо, чеснок, соль, приправы",
      "Хорошо перемешать и скатать тефтели",
      "Разогреть сковороду с каплей оливкового масла",
      "Обжарить тефтели с двух сторон до золотистой корочки",
      "Отварить гречку на гарнир",
      "К каждой порции добавить 100 г помидора"
    ]
  },
  {
    "name": "Курица в сладком соусе с рисом",
    "type": "обед",
    "time": "",
    "ingredients": [
      "Куриная грудка - 200 г",
      "Болгарский перец - 100 г",
      "Рис - 100 г",
      "Чеснок - 2 зубчика",
      "Соус соевый - 40 г",
      "Томатная паста - 30 г",
      "Сахар - 1 ч.л (или сахарозаменитель)",
      "Огурец - 200 г"
    ],
    "instructions": [
      "Отварить рис",
      "Куриную грудку нарезать тонкими кусочками",
      "Перец нарезать соломкой",
      "Чеснок мелко нарубить",
      "Обжарить курицу без масла, добавить чеснок и перец",
      "Для соуса смешать соевый соус, томатную пасту и сахар",
      "Влить соус в сковороду, тушить курицу 20 минут",
      "В конце добавить рис, все перемешать",
      "К каждой порции добавить по 100 г огурца"
    ]
  },
  {
    "name": "Ленивый пирог из лаваша",
    "type": "обед",
    "time": "",
    "ingredients": [
      "Лаваш - 130 г",
      "Куриное филе - 130 г",
      "Сыр - 80 г",
      "Яйцо - 1 шт",
      "Молоко - 80 мл"
    ],
    "instructions": [
      "Лаваш свернуть в рулет, нарезать на кусочки ножницами",
      "Куриное филе приготовить любым способом (отварить/обжарить без масла), нарезать",
      "Добавить курицу к лавашу",
      "Сыр натереть, добавить к курице и лавашу",
      "Добавить яйцо и молоко, все перемешать",
      "Выложить на разогретую сковороду (без масла), придать форму",
      "Жарить под крышкой на среднем огне ~5 минут до зарумянивания",
      "Перевернуть пирог и жарить еще ~5 минут с другой стороны под крышкой"
    ]
  },
  {
    "name": "Сытный салат + картофель",
    "type": "обед",
    "time": "",
    "ingredients": [
      "Картофель - 250 г",
      "Сливочное масло - 5 г",
      "Говядина - 200 г",
      "Красный лук - 100 г",
      "Болгарский перец - 150 г",
      "Сметана 15% - 60 г",
      "Лимонный сок - 1 ч.л",
      "Соль - по вкусу"
    ],
    "instructions": [
      "Говядину отварить, разорвать на волокна",
      "Лук и болгарский перец нарезать",
      "Смешать говядину, лук, перец",
      "Заправить сметаной, лимонным соком, посолить по вкусу",
      "Картофель отварить, добавить сливочное масло",
      "Можно из картофеля сделать пюре"
    ]
  },
  {
    "name": "Сырный суп с шампиньонами и брокколи",
    "type": "обед",
    "time": "",
    "ingredients": [
      "Шампиньоны - 300 г",
      "Сырок плавленный - 180 г (2 шт)",
      "Брокколи - 200 г",
      "Картофель - 100 г",
      "Морковь - 75 г",
      "Соль - по вкусу"
    ],
    "instructions": [
      "Шампиньоны нарезать, обжарить 5-10 минут",
      "Морковь натереть на терке и обжарить",
      "Брокколи разделить на соцветия",
      "Картошку нарезать",
      "В кипящую воду добавить все ингредиенты, посолить",
      "Варить в течение 10 минут",
      "Сырки натереть на крупную терку",
      "Добавить в суп, варить еще 5 минут до растворения сырков",
      "Посыпать сушеным укропом (по желанию), дать потомиться пару минут"
    ]
  },
  {
    "name": "Куриные ёжики с рисом",
    "type": "обед",
    "time": "",
    "ingredients": [
      "Куриный фарш - 250 г",
      "Лук репчатый - 70 г",
      "Морковь - 40 г",
      "Рис - 90 г",
      "Сметана 15% - 25 г",
      "Томатная паста - 25 г",
      "Яйцо - 1 шт",
      "Сыр - 40 г",
      "Соль, перец - по вкусу"
    ],
    "instructions": [
      "Смешать сухой рис с фаршем и мелко нарубленным луком",
      "Добавить яйцо для вязкости",
      "Солить, перчить по вкусу",
      "Сформировать ежики желаемого размера",
      "Для заливки: шинковать лук и морковь, смешать со сметаной и томатной пастой",
      "Залить смесь кипяченой водой (ежики должны быть почти полностью закрыты)",
      "Накрыть фольгой и запекать при 180-190°C 40-50 минут",
      "За 10 минут до готовности снять фольгу, посыпать тертым сыром",
      "Запекать до образования аппетитной корочки"
    ]
  },
  {
    "name": "ПП-оливье с рыбкой",
    "type": "обед",
    "time": "",
    "ingredients": [
      "Семга слабосоленая - 130 г (можно заменить на отварную курицу)",
      "Картофель - 200 г",
      "Морковь - 50 г",
      "Яйцо - 2 шт",
      "Горошек консервированный - 150 г",
      "Огурцы корнишоны - 80 г (можно заменить на свежие)",
      "Сметана 15% - 80 г"
    ],
    "instructions": [
      "Яйца, картофель и морковь отварить",
      "Все ингредиенты салата нарезать",
      "Соединить в миске",
      "Заправить сметаной и посолить по вкусу"
    ]
  },
  {
    "name": "Гречка с курицей и грибами",
    "type": "обед",
    "time": "",
    "ingredients": [
      "Куриная грудка - 250 г",
      "Гречка - 100 г (в сухом виде)",
      "Шампиньоны - 200 г",
      "Лук - 50 г",
      "Морковь - 50 г",
      "Соль/перец/специи - по вкусу",
      "Растительное масло - 10 г",
      "Огурец - 200 г"
    ],
    "instructions": [
      "Отварить гречку, посолить по вкусу",
      "Нарезать курицу, лук, шампиньоны",
      "Морковь натереть на терке",
      "На сковороде разогреть масло, добавить курицу, обжарить 2 минуты",
      "Добавить лук, морковь и шампиньоны",
      "Добавить соль/перец/специи по вкусу",
      "Обжарить до готовности, перемешать с гречкой",
      "К каждой порции добавить по 100 г огурца"
    ]
  },
  {
    "name": "Творог с яблоком, корицей и миндалем",
    "type": "десерт",
    "time": "",
    "ingredients": [
      "Творог мягкий обезжиренный - 170 г",
      "Яблоко - 80 г",
      "Корица - по вкусу",
      "Миндаль - 10 г"
    ],
    "instructions": [
      "К творогу добавить мелко нарезанное яблоко",
      "Добавить миндаль",
      "Посыпать корицей по вкусу",
      "По желанию можно добавить подсластитель",
      "Ингредиенты указаны на 1 раз"
    ]
  },
  {
    "name": "Салат из свеклы",
    "type": "десерт",
    "time": "",
    "ingredients": [
      "Свекла - 125 г (предварительно отваренная)",
      "Огурец - 100 г",
      "Чеснок - 2 зубчика",
      "Сметана 15% - 35 г"
    ],
    "instructions": [
      "Свеклу натереть на терке",
      "Огурец нарезать соломкой",
      "Чеснок измельчить",
      "Все смешать и заправить сметаной",
      "Посолить по вкусу",
      "Ингредиенты указаны на 1 раз"
    ]
  },
  {
    "name": "Шоколад горький",
    "type": "десерт",
    "time": "",
    "ingredients": [
      "Шоколад горький - 50 г"
    ],
    "instructions": [
      "50 г шоколада разделить на 2 перекуса",
      "На каждый перекус брать по 25 г"
    ]
  },
  {
    "name": "Миндаль",
    "type": "десерт",
    "time": "",
    "ingredients": [
      "Миндаль - 50 г (можно заменить любыми другими орехами)"
    ],
    "instructions": [
      "50 г миндаля разделить на 2 перекуса",
      "На каждый перекус брать по 25 г"
    ]
  },
  {
    "name": "Банан",
    "type": "десерт",
    "time": "",
    "ingredients": [
      "Банан - 1 шт"
    ],
    "instructions": [
      "На каждый перекус брать по 1 банану"
    ]
  },
  {
    "name": "Яйцо с сыром и огурцом",
    "type": "десерт",
    "time": "",
    "ingredients": [
      "Яйцо отварное - 1 шт",
      "Сыр - 25 г",
      "Огурец - 100 г"
    ],
    "instructions": [
      "Продукты указаны на 1 раз",
      "На следующий день можно повторить такой же перекус"
    ]
  },
  {
    "name": "Йогурт питьевой",
    "type": "десерт",
    "time": "",
    "ingredients": [
      "Йогурт питьевой натуральный - 290 г"
    ],
    "instructions": [
      "На каждый перекус брать по 290 г йогурта"
    ]
  },
  {
    "name": "Бутерброд с сыром и огурцом",
    "type": "десерт",
    "time": "",
    "ingredients": [
      "Хлеб зерновой - 25 г",
      "Сыр - 25 г",
      "Огурец - 40 г"
    ],
    "instructions": [
      "Продукты указаны на 1 раз",
      "На следующий день можно повторить такой же перекус"
    ]
  },
  {
    "name": "Ряженка с яблоком",
    "type": "десерт",
    "time": "",
    "ingredients": [
      "Ряженка 3,2% - 200 г (можно заменить на кефир/питьевой йогурт)",
      "Яблоко - 165 г"
    ],
    "instructions": [
      "Продукты указаны на 1 раз",
      "На следующий день можно повторить такой же перекус"
    ]
  },
  {
    "name": "Протеиновое печенье",
    "type": "десерт",
    "time": "",
    "ingredients": [
      "Печенье протеиновое - 60 г (например Bombbar)"
    ],
    "instructions": [
      "Можно взять печенье других фирм",
      "Главное - читать состав (без сахара, пшеничной муки и масла)"
    ]
  },
  {
    "name": "Сытный белковый салат",
    "type": "ужин",
    "time": "",
    "ingredients": [
      "Тунец в собственном соку - 180 г (можно заменить на курицу/индейку/другую рыбу)",
      "Сыр - 80 г",
      "Шампиньоны - 200 г",
      "Яйцо - 2 шт",
      "Огурец - 200 г",
      "Сметана 15% - 80 г",
      "Горчица - 6 г",
      "Чеснок - 2 зубчика"
    ],
    "instructions": [
      "Яйца отварить",
      "Шампиньоны нарезать, обжарить без масла или отварить",
      "Сыр натереть на крупной тёрке или нарезать кубиками",
      "Огурец нарезать произвольной формой",
      "Яйца мелко нарубить",
      "Для заправки смешать сметану, горчицу и чеснок",
      "Соединить в тарелке тунец, сыр, шампиньоны, яйца, огурец",
      "Добавить заправку и перемешать"
    ]
  },
  {
    "name": "Куриные гнезда с сыром",
    "type": "ужин",
    "time": "",
    "ingredients": [
      "Куриная грудка - 300 г",
      "Яйцо - 2 шт",
      "Сыр - 55 г",
      "Помидор - 50 г",
      "Молоко 1,5% - 35 г",
      "Огурец - 200 г"
    ],
    "instructions": [
      "Грудку нарезать, добавить 1 яйцо",
      "Поперчить/посолить по вкусу",
      "Измельчить блендером",
      "Сыр натереть на мелкой тёрке",
      "К измельченной грудке добавить сыр и молоко, перемешать",
      "В отдельной миске смешать 1 яйцо и нарезанный помидор",
      "Сформировать из фарша большие котлеты",
      "Сделать углубления влажными руками или смоченным стаканом",
      "Выложить столовой ложкой смесь яиц и помидора в углубления",
      "Отправить в духовку на полчаса при 200 градусах",
      "Подавать с нарезанным огурцом"
    ]
  },
  {
    "name": "Курица с овощами",
    "type": "ужин",
    "time": "",
    "ingredients": [
      "Куриное филе - 260 г",
      "Морковь - 140 г",
      "Брокколи - 260 г",
      "Лук репчатый - 60 г",
      "Соус соевый - 50 г",
      "Масло растительное - 1 ст.л",
      "Специи по вкусу: копченая паприка, кориандр, чёрный перец, сушеные томаты, соль"
    ],
    "instructions": [
      "Нарезать куриную грудку",
      "Лук и морковь нарезать соломкой",
      "Брокколи разобрать на соцветия",
      "Брокколи по желанию можно отварить 2 минуты",
      "В сковороде разогреть масло",
      "Обжарить курицу, добавить лук, морковь и брокколи",
      "Для соуса смешать соевый соус и специи",
      "Добавить соус к овощам, перемешать и снять с огня",
      "Соль добавлять немного, так как соевый соус сам по себе соленый"
    ]
  },
  {
    "name": "Сырно-чесночные отбивные из индейки с салатом",
    "type": "ужин",
    "time": "",
    "ingredients": [
      "Индейка (филе) - 300 г",
      "Сыр - 40 г",
      "Чеснок - 3 зубчика",
      "Соль/специи - по вкусу",
      "Растительное масло - 5 г",
      "Огурец - 200 г",
      "Редис - 100 г",
      "Яйцо отварное - 1 шт",
      "Сметана 15% - 40 г"
    ],
    "instructions": [
      "Филе индейки отбить",
      "На сковороде разогреть каплю масла",
      "Индейку посолить, смазать специями по вкусу",
      "Чеснок раздавить в чеснокодавилке, обмазать отбивные со всех сторон",
      "Обжарить отбивную с одной стороны",
      "Перевернуть на другую, сверху посыпать сыром",
      "Жарить до готовности",
      "Для салата: отварить яйцо, нарезать его, огурец и редис",
      "Заправить сметаной, посолить по вкусу"
    ]
  },
  {
    "name": "Салат Щётка + говядина",
    "type": "ужин",
    "time": "",
    "ingredients": [
      "Говядина - 200 г",
      "Соль, перец - по вкусу",
      "Свекла - 1 шт",
      "Морковь - 2 шт",
      "Капуста белокочанная - 300 г",
      "Оливковое масло - 2 ст. ложки",
      "Лимонный сок - 1 ч. ложка",
      "Соль, перец - по вкусу"
    ],
    "instructions": [
      "Все овощи использовать в сыром виде",
      "Морковь и свёклу очистить, натереть на терке",
      "Капусту нашинковать",
      "Все ингредиенты смешать",
      "Заправить маслом, добавить сок лимона, соль/перец по вкусу",
      "Говядину отварить"
    ]
  },
  {
    "name": "Азиатский салат",
    "type": "ужин",
    "time": "",
    "ingredients": [
      "Говядина - 200 г",
      "Болгарский перец - 200 г",
      "Огурец - 200 г",
      "Чеснок - 2 зубчика",
      "Кунжут - 10 г (по желанию)",
      "Соевый соус - 55 мл",
      "Хмели сунели - 1 чайная ложка",
      "Растительное масло - 15 мл",
      "Соль и чёрный перец - по вкусу"
    ],
    "instructions": [
      "Мясо нарезать на брусочки",
      "Сделать маринад: смешать соевый соус, хмели-сунели",
      "Добавить маринад к мясу, перемешать, оставить на 15 минут",
      "Огурец и болгарский перец нарезать толстыми брусочками",
      "На сковороде разогреть масло, добавить мелко нарезанный чеснок",
      "Обжарить мясо",
      "Готовое мясо переложить к овощам и посыпать кунжутом",
      "Можно посолить/поперчить по вкусу"
    ]
  },
  {
    "name": "Омлет с помидорами и сыром",
    "type": "ужин",
    "time": "",
    "ingredients": [
      "Яйца - 2 шт",
      "Молоко 1,5% - 20 мл",
      "Помидор - 100 г",
      "Сыр - 30 г",
      "Зеленый лук - 25 г"
    ],
    "instructions": [
      "На сковороде без масла обжарить помидор и мелко нарезанный лук",
      "Смешать яйца, молоко, посолить по вкусу",
      "Вылить яично-молочную смесь на сковороду",
      "За минуту до снятия с огня посыпать тертым сыром",
      "Ингредиенты указаны на 1 порцию"
    ]
  },
  {
    "name": "Рыбка запеченная с овощами",
    "type": "ужин",
    "time": "",
    "ingredients": [
      "Лосось - 300 г",
      "Брокколи - 200 г",
      "Морковь - 70 г",
      "Лук-шалот или обычный - 40 г",
      "Помидор - 100 г",
      "Соус соевый - 30 г",
      "Соль/перец - по вкусу",
      "Масло растительное - 1 ст.л",
      "Специи: розмарин, кориандр, чеснок сушеный"
    ],
    "instructions": [
      "Морковь нарезать кружочками",
      "Капусту разобрать на соцветия",
      "Помидоры нарезать дольками",
      "Лук нарезать дольками",
      "Морковь поставить варить на 10 минут, через 5 минут добавить брокколи",
      "В форму выложить овощную подушку из помидоров, лука, брокколи и моркови",
      "Полить овощи маслом, перемешать",
      "Рыбу замариновать в соевом соусе, добавить соль, специи по вкусу",
      "Выложить рыбу на овощную подушку",
      "Запекать в духовке около 25 минут при 180 градусах"
    ]
  },
  {
    "name": "Сытный салат",
    "type": "ужин",
    "time": "",
    "ingredients": [
      "Куриное филе - 140 г",
      "Шампиньоны - 100 г",
      "Репчатый лук - 20 г",
      "Огурец - 100 г",
      "Маринованные огурцы - 50 г",
      "Яйцо - 1 шт",
      "Сметана 15% - 40 г",
      "Оливковое масло - 15 г",
      "Соль - по вкусу"
    ],
    "instructions": [
      "Яйцо отварить и мелко нарезать",
      "Все остальные ингредиенты мелко нарезать",
      "Обжарить на оливковом масле лук",
      "Добавить грибы, затем курицу",
      "Жарить до золотистой корочки",
      "Смешать всё, посолить/поперчить по желанию",
      "Заправить сметаной"
    ]
  },
  {
    "name": "Лодочки из кабачков с курицей",
    "type": "ужин",
    "time": "",
    "ingredients": [
      "Кабачок средний - 2 шт",
      "Помидор - 200 г",
      "Куриная грудка - 200 г",
      "Сыр - 80 г",
      "Сметана 15% - 80 г",
      "Соль/перец - по вкусу",
      "Специи по вкусу (итальянские травы, орегано)"
    ],
    "instructions": [
      "Кабачок разрезать вдоль, ложкой вырезать сердцевину",
      "Нарезать курицу, помидор",
      "Добавить приправы, посолить",
      "Выложить все в кабачки и сверху полить сметаной",
      "Отправить в духовку на 25-30 минут при 180 градусах",
      "Достать, посыпать сыром и запекать ещё 5 минут"
    ]
  },
  {
    "name": "Блинный ПП-тортик",
    "type": "десерт",
    "time": "",
    "ingredients": [
      "Мука рисовая - 180 г",
      "Яйца - 3 шт",
      "Молоко - 180 мл",
      "Разрыхлитель - ½ ч.л",
      "Сахарозаменитель - по вкусу",
      "Молоко - 500 мл (для крема)",
      "Кукурузный крахмал - 30 г (для крема)",
      "Яйцо - 1 шт (для крема)",
      "Сахарозаменитель - по вкусу (для крема)",
      "Ванилин - по вкусу (для крема)",
      "Клубника - 200 г (для прослойки)"
    ],
    "instructions": [
      "Для блинов: смешать все ингредиенты, дать тесту постоять 8-10 минут",
      "Выпекать на сухой, сильно разогретой сковороде с двух сторон",
      "Для крема: налить молоко в кастрюлю и поставить на огонь",
      "Смешать яйцо с сахарозаменителем и ванилином",
      "Не доводя молоко до кипения, осторожно влить яичную смесь, постоянно помешивая",
      "Крахмал растворить в воде (50 г воды), добавить в молоко",
      "Постоянно помешивать крем до загустения",
      "Собрать торт: на блюдо выложить остывший блин, промазать кремом и выложить нарезанную клубнику",
      "Повторить с каждым слоем",
      "Верхний слой промазать кремом",
      "Украсить по желанию, посыпать какао",
      "Порция 300 г - на завтрак, 180 г - на перекус"
    ]
  },
  {
    "name": "Тирамису в ПП-версии",
    "type": "десерт",
    "time": "",
    "ingredients": [
      "Яйцо - 4 шт (для коржа)",
      "Крахмал кукурузный - 30 г (для коржа)",
      "Сахарозаменитель - по вкусу (для коржа)",
      "Разрыхлитель - ½ ч.л (для коржа)",
      "Вода - 200 мл (для пропитки)",
      "Кофе - 1 ч.л (для пропитки)",
      "Творог мягкий 5% - 200 г (для крема)",
      "Сахарозаменитель - по вкусу (для крема)",
      "Какао - 1 ч.л (для посыпки)"
    ],
    "instructions": [
      "Приготовить корж: отделить белки от желтков",
      "Смешать желтки, крахмал, сахарозаменитель, разрыхлитель",
      "Взбить белки отдельно и вмешать в желтковую массу",
      "Выпекать 10 минут при 180°C",
      "Разрезать корж на квадратики",
      "Приготовить пропитку: заварить кофе в 200 мл воды",
      "Окунуть каждый кусочек коржа в кофе",
      "В творог добавить сахарозаменитель по вкусу",
      "Собрать десерт: выложить творог, кусочки бисквита, творог и т.д.",
      "Сверху присыпать какао",
      "Убрать в холодильник на пару часов"
    ]
  },
  {
    "name": "Кокосовый ПП-торт",
    "type": "десерт",
    "time": "",
    "ingredients": [
      "Мука рисовая - 100 г (для бисквита)",
      "Яйцо - 1 целое + 2 белка (для бисквита)",
      "Сметана 15% - 50 г (для бисквита)",
      "Разрыхлитель - 1 ч.л (для бисквита)",
      "Соль - щепотка (для бисквита)",
      "Подсластитель - по вкусу (для бисквита)",
      "Теплая вода - 100-150 мл (для пропитки)",
      "Подсластитель - по вкусу (для пропитки)",
      "Молоко 0,5% - 200 мл (для крема)",
      "Желток - 1 шт (для крема)",
      "Кукурузный крахмал - 15 г (для крема)",
      "Кокосовая стружка - 20 г (для крема)",
      "Кокосовая стружка - 10 г (для посыпки)"
    ],
    "instructions": [
      "Приготовить бисквит: яйцо и белки взбить с щепоткой соли до увеличения массы",
      "Просейть муку с разрыхлителем, добавить сметану",
      "Перемешать до однородности",
      "Выпекать в силиконовой форме диаметром 17 см ~14 минут при 180°C",
      "Готовность проверять зубочисткой",
      "Готовый корж разрезать вдоль на 2 части",
      "Приготовить пропитку: смешать теплую воду с подсластителем",
      "Пропитать коржи с помощью кисти",
      "Приготовить крем: 180 мл молока подогреть в кастрюле (не кипятить)",
      "Отдельно перемешать 20 мл молока с желтком, крахмалом, кокосовой стружкой и подсластителем",
      "Добавить к подогретому молоку и варить на медленном огне до загустения",
      "Промазать коржи кремом",
      "Посыпать торт стружкой и оставить пропитаться (лучше на ночь)"
    ]
  },
  {
    "name": "ПП-сочники",
    "type": "десерт",
    "time": "",
    "ingredients": [
      "Рисовая мука - 150 г",
      "Яйцо - 1 шт",
      "Йогурт натуральный - 50 мл",
      "Подсластитель - по вкусу",
      "Разрыхлитель - ½ ч.л",
      "Желток - 1 шт (для корочки)",
      "Молоко 1,5% - 10 мл (для корочки)",
      "Творог 2% - 180 г (для начинки)",
      "Йогурт натуральный - 40 мл (для начинки)",
      "Подсластитель - по вкусу (для начинки)",
      "Ванилин - по вкусу (для начинки)"
    ],
    "instructions": [
      "Смешать ингредиенты для теста (оно должно быть эластичным и не липнуть к рукам)",
      "Отправить тесто в холодильник на 30 минут",
      "Для начинки: творог, йогурт, подсластитель смешать и тщательно перемешать",
      "Достать тесто из холодильника и раскатать толщиной 0,5 см",
      "Вырезать стаканом кружочки",
      "На половину кружочка выложить начинку",
      "Накрыть второй частью",
      "Смешать молоко с желтком и смазать сочники",
      "Отправить в духовку на 25 минут при 180 градусах"
    ]
  },
  {
    "name": "Наполеон в ПП-версии",
    "type": "десерт",
    "time": "",
    "ingredients": [
      "Лаваш - 200 г",
      "Молоко 1,5% - 400 мл",
      "Сухое обезжиренное молоко - 100 г",
      "Крахмал кукурузный - 50 г",
      "Подсластитель - по вкусу",
      "Ванилин - по вкусу"
    ],
    "instructions": [
      "Из лаваша вырезать коржи нужной формы (круглые или квадратные)",
      "Подсушить в духовке, чтобы они хрустели и ломались",
      "Приготовить крем: смешать молоко, сухое обезжиренное молоко, крахмал, подсластитель и ванилин в кастрюле",
      "Варить, постоянно помешивая, до загустения",
      "Собрать торт: промазывать коржи кремом",
      "Остатки коржей поломать и посыпать сверху"
    ]
  }
]